ssc4onnx/__init__.py
ssc4onnx/__main__.py
ssc4onnx/onnx_structure_check.py
ssc4onnx-1.0.8.dist-info/LICENSE
ssc4onnx-1.0.8.dist-info/METADATA
ssc4onnx-1.0.8.dist-info/WHEEL
ssc4onnx-1.0.8.dist-info/entry_points.txt
ssc4onnx-1.0.8.dist-info/top_level.txt
ssc4onnx-1.0.8.dist-info/RECORD
