Metadata-Version: 2.1
Name: ssc4onnx
Version: 1.0.8
Summary: Checker with simple ONNX model structure. Simple Structure Checker for ONNX.
Home-page: https://github.com/PINTO0309/ssc4onnx
Author: Katsuya Hyodo
Author-email: rmsdh122@yahoo.co.jp
License: MIT License
Platform: linux
Platform: unix
Requires-Python: >=3.6
License-File: LICENSE
